<?xml version="1.0" encoding="utf-8"?>
<Root xmlns="http://tempuri.org/XMLSchema.xsd">
  <Category Name="Global Objects">
    <Object Id="6500" Name="Itembox">
      <Description>Just a simple itembox. Common used.</Description>
      <Picture>http://www.dshack.org/wiki/images/3/3c/Itembox.png</Picture>
      <Files>
        <File FileName="itembox.nsbmd" />
        <File FileName="itembox.nsbca" />
        <File FileName="itembox_shadow.nsbmd" />
        <File FileName="itembox_hahen.nsbmd" />
        <File FileName="obj_shadow.nsbmd" />
      </Files>
      <Setting Id="0">
        <U16 Hex="true" />
        <U16 Name="What's Inside" />
      </Setting>
      <Setting Id="1">
        <U32 Hex="true" />
      </Setting>
      <Setting Id="2">
        <U32 Hex="true" />
      </Setting>
      <Setting Id="3">
        <U32 Hex="true" />
      </Setting>
    </Object>
    <Object Id="C900" Name="Moving Itembox">
      <Description>An itembox that follows a route. Without a route, it causes a crash on a real ds.</Description>
      <Picture>http://www.dshack.org/wiki/images/3/3c/Itembox.png</Picture>
      <Route Required="true" />
      <Files>
        <File FileName="itembox.nsbmd" />
        <File FileName="itembox.nsbca" />
        <File FileName="itembox_shadow.nsbmd" />
        <File FileName="itembox_hahen.nsbmd" />
        <File FileName="obj_shadow.nsbmd" />
      </Files>
      <Setting Id="0">
        <S16 Name="Route Speed" />
        <U16 Name="Content" />
      </Setting>
      <Setting Id="1">
        <S32 Name="Roulette Speed" />
      </Setting>
      <Setting Id="2">
        <U16 Hex="true" />
        <S16 Name="Respawnability" />
      </Setting>
      <Setting Id="3">
        <S32 Name="Respawn Time" />
      </Setting>
    </Object>
    <Object Id="6D00" Name="Item">
      <Files>
        <File FileName="it_banana.nsbmd" />
        <File FileName="it_bomb.nsbmd" />
        <File FileName="it_kinoko.nsbmd" />
        <File FileName="it_kinoko_p.nsbmd" />
        <File FileName="it_koura_g.nsbmd" />
        <File FileName="it_koura_r.nsbmd" />
        <File FileName="it_star.nsbmd" />
        <File FileName="it_f_box.nsbmd" />
        <File FileName="it_bomb.nsbtp" />
      </Files>
      <Setting Id="0">
        <U32 Hex="true" />
      </Setting>
      <Setting Id="1">
        <U32 Hex="true" />
      </Setting>
      <Setting Id="2">
        <U32 Hex="true" />
      </Setting>
      <Setting Id="3">
        <U32 Hex="true" />
      </Setting>
    </Object>
    <Object Id="6600" Name="Pole">
      <Description>Collision-only. Mostly used for making the poles at the start of the race collide.</Description>
      <Files />
      <Setting Id="0">
        <U32 Hex="true" />
      </Setting>
      <Setting Id="1">
        <U32 Hex="true" />
      </Setting>
      <Setting Id="2">
        <U32 Hex="true" />
      </Setting>
      <Setting Id="3">
        <U32 Hex="true" />
      </Setting>
    </Object>
    <Category Name="Mission Objects">
      <Object Id="6800" Name="Coin">
        <Description>Used in missions. Useless in other situations.</Description>
        <Picture>http://gamestemple.files.wordpress.com/2012/10/coins.png?w=150&amp;h=150</Picture>
        <Files>
          <File FileName="coin.nsbmd" />
          <File FileName="coin.nsbtp" />
        </Files>
        <Setting Id="0">
          <U32 Hex="true" />
        </Setting>
        <Setting Id="1">
          <U32 Hex="true" />
        </Setting>
        <Setting Id="2">
          <U32 Hex="true" />
        </Setting>
        <Setting Id="3">
          <U32 Hex="true" />
        </Setting>
      </Object>
      <Object Id="6E00" Name="Mission Gate">
        <Description>Gates you'll have to drive through to finish the mission.</Description>
        <Files>
          <File FileName="MissionGate.nsbmd" />
          <File FileName="MissionGate.nsbtp" />
          <File FileName="MissionGate.nsbma" />
        </Files>
        <Setting Id="0">
          <S32 Name="Gate Nr" />
        </Setting>
        <Setting Id="1">
          <U32 Hex="true" />
        </Setting>
        <Setting Id="2">
          <U32 Hex="true" />
        </Setting>
        <Setting Id="3">
          <U32 Hex="true" />
        </Setting>
      </Object>
      <Object Id="5901" Name="Stop Sign">
        <Description>The stop sign used in the mission run. It doesn't collide, so you'll have to use a wall (0B00) to make those things really stop the player from passing them.</Description>
        <Files>
          <File FileName="StopSign.nsbmd" />
        </Files>
        <Setting Id="0">
          <U32 Hex="true" />
        </Setting>
        <Setting Id="1">
          <U32 Hex="true" />
        </Setting>
        <Setting Id="2">
          <U32 Hex="true" />
        </Setting>
        <Setting Id="3">
          <U32 Hex="true" />
        </Setting>
      </Object>
      <Object Id="0B00" Name="Wall">
        <Files />
        <Setting Id="0">
          <U32 Hex="true" />
        </Setting>
        <Setting Id="1">
          <U32 Hex="true" />
        </Setting>
        <Setting Id="2">
          <U32 Hex="true" />
        </Setting>
        <Setting Id="3">
          <U32 Hex="true" />
        </Setting>
      </Object>
      <Category Name="Bosses">
        <Object Id="FD01" Name="King Teresa">
          <Picture>http://www.mariowiki.com/images/1/16/King_BooMKDS.png</Picture>
          <Route Required="true" />
          <Files>
            <File FileName="king_teresa.nsbmd" />
            <File FileName="king_teresa.nsbca" />
            <File FileName="king_teresa.prm" />
            <File FileName="sh_circle.nsbmd" />
          </Files>
          <Setting Id="0">
            <U32 Name="Unknown1" Hex="true" />
          </Setting>
          <Setting Id="1">
            <U32 Name="Unknown2" Hex="true" />
          </Setting>
          <Setting Id="2">
            <U32 Name="Unknown3" Hex="true" />
          </Setting>
          <Setting Id="3">
            <U32 Name="Unknown4" Hex="true" />
          </Setting>
        </Object>
        <Object Id="FC01" Name="Wiggler (Head)">
          <Picture>http://www.mariowiki.com/images/thumb/7/7c/WigglerDS.png/150px-WigglerDS.png</Picture>
          <Route Required="true" />
          <Files>
            <File FileName="hanachan.nsbmd" />
            <File FileName="hanachan.nsbca" />
            <File FileName="hanachan.nsbtp" />
            <File FileName="hanachan.prm" />
            <File FileName="hanachan_1.nsbmd" />
            <File FileName="hanachan_1.nsbca" />
            <File FileName="hanachan_1.nsbtp" />
            <File FileName="hanachan_2.nsbmd" />
            <File FileName="hanachan_2.nsbca" />
            <File FileName="hanachan_3.nsbmd" />
            <File FileName="hanachan_4.nsbmd" />
            <File FileName="sh_circle.nsbmd" />
          </Files>
          <Setting Id="0">
            <U32 Name="Unknown1" Hex="true" />
          </Setting>
          <Setting Id="1">
            <U32 Name="Unknown2" Hex="true" />
          </Setting>
          <Setting Id="2">
            <U32 Name="Unknown3" Hex="true" />
          </Setting>
          <Setting Id="3">
            <U32 Name="Unknown4" Hex="true" />
          </Setting>
        </Object>
        <Object Id="FE01" Name="Wiggler (Body)">
          <Route Required="true" />
          <Files />
          <Setting Id="0">
            <U32 Name="Unknown1" Hex="true" />
          </Setting>
          <Setting Id="1">
            <U32 Name="Unknown2" Hex="true" />
          </Setting>
          <Setting Id="2">
            <U32 Name="Unknown3" Hex="true" />
          </Setting>
          <Setting Id="3">
            <U32 Name="Unknown4" Hex="true" />
          </Setting>
        </Object>
      </Category>
    </Category>
  </Category>
  <Category Name="Enemies">
    <Object Id="AA01" Name="Big Fire Piranha Plant">
      <Description>Used in Mario Circuit. Spits fire balls which follow the routes defined in the settings. A route may be omitted by making it -1.</Description>
      <Picture>http://images1.wikia.nocookie.net/__cb20110913221526/mario/images/thumb/5/51/Piranha_Plant_Artwork_(Super_Mario_3D_Land).png/83px-Piranha_Plant_Artwork_(Super_Mario_3D_Land).png</Picture>
      <Files>
        <File FileName="PakkunBody.nsbmd" />
        <File FileName="PakkunMouth.nsbmd" />
        <File FileName="PakkunZHead.nsbmd" />
        <File FileName="fireball.nsbmd" />
        <File FileName="PakkunMouth.nsbca" />
      </Files>
      <Setting Id="0">
        <S16 Name="Fire Route ID 1" />
        <S16 Name="Fire Route ID 2" />
      </Setting>
      <Setting Id="1">
        <S16 Name="Fire Route ID 3" />
        <S16 Name="Fire Route ID 4" />
      </Setting>
      <Setting Id="2">
        <S16 Name="Fire Route ID 5" />
        <S16 Name="Fire Route ID 6" />
      </Setting>
      <Setting Id="3">
        <S16 Name="Fire Route ID 7" />
        <U16 Hex="true" />
      </Setting>
    </Object>
    <Object Id="9601" Name="Chain Chomp">
      <Picture>http://www.dshack.org/wiki/images/5/5c/Wanwan.png</Picture>
      <Files>
        <File FileName="wanwan.nsbmd" />
        <File FileName="wanwan_chain.nsbmd" />
        <File FileName="wanwan_kui.nsbmd" />
        <File FileName="rock_shadow.nsbmd" />
      </Files>
      <Setting Id="0">
        <U32 Hex="true" />
      </Setting>
      <Setting Id="1">
        <U32 Hex="true" />
      </Setting>
      <Setting Id="2">
        <U32 Hex="true" />
      </Setting>
      <Setting Id="3">
        <U32 Hex="true" />
      </Setting>
    </Object>
    <Object Id="A501" Name="Moving Chain Chomp">
      <Picture>http://www.dshack.org/wiki/images/5/5c/Wanwan.png</Picture>
      <Route Required="true" />
      <Files>
        <File FileName="wanwan.nsbmd" />
        <File FileName="wanwan_chain.nsbmd" />
        <File FileName="rock_shadow.nsbmd" />
      </Files>
      <Setting Id="0">
        <U32 Hex="true" />
      </Setting>
      <Setting Id="1">
        <U32 Hex="true" />
      </Setting>
      <Setting Id="2">
        <U32 Hex="true" />
      </Setting>
      <Setting Id="3">
        <U32 Hex="true" />
      </Setting>
    </Object>
    <Object Id="AC01" Name="Crab">
      <Picture>http://www.dshack.org/wiki/images/6/63/Crab.png</Picture>
      <Files>
        <File FileName="crab.nsbmd" />
        <File FileName="crab_hand.nsbmd" />
        <File FileName="crab.nsbtp" />
        <File FileName="crab_hand.nsbtp" />
      </Files>
      <Setting Id="0">
        <U32 Hex="true" />
      </Setting>
      <Setting Id="1">
        <U32 Hex="true" />
      </Setting>
      <Setting Id="2">
        <U32 Hex="true" />
      </Setting>
      <Setting Id="3">
        <U32 Hex="true" />
      </Setting>
    </Object>
    <Object Id="9B01" Name="Cheep Cheep">
      <Picture>http://www.dshack.org/wiki/images/d/db/Cheepcheep.png</Picture>
      <Files>
        <File FileName="pukupuku.nsbmd" />
      </Files>
      <Setting Id="0">
        <U32 Hex="true" />
      </Setting>
      <Setting Id="1">
        <U32 Hex="true" />
      </Setting>
      <Setting Id="2">
        <U32 Hex="true" />
      </Setting>
      <Setting Id="3">
        <U32 Hex="true" />
      </Setting>
    </Object>
    <Object Id="9101" Name="Goomba">
      <Picture>http://www.iconspedia.com/dload.php?up_id=15375</Picture>
      <Route Required="true" />
      <Files>
        <File FileName="kuribo.nsbmd" />
        <File FileName="kuribo.nsbtp" />
      </Files>
      <Setting Id="0">
        <U32 Hex="true" />
      </Setting>
      <Setting Id="1">
        <U32 Hex="true" />
      </Setting>
      <Setting Id="2">
        <U32 Hex="true" />
      </Setting>
      <Setting Id="3">
        <U32 Hex="true" />
      </Setting>
    </Object>
    <Object Id="A601" Name="Piranha Plant">
      <Picture>http://www.dshack.org/wiki/images/2/21/Pukkun_sf.png</Picture>
      <Files>
        <File FileName="ob_pakkun_sf.nsbmd" />
        <File FileName="ob_pakkun_sf.nsbtp" />
      </Files>
      <Setting Id="0">
        <U32 Hex="true" />
      </Setting>
      <Setting Id="1">
        <U32 Hex="true" />
      </Setting>
      <Setting Id="2">
        <U32 Hex="true" />
      </Setting>
      <Setting Id="3">
        <U32 Hex="true" />
      </Setting>
    </Object>
    <Object Id="A301" Name="Luigi Mansions Moving Tree">
      <Route Required="true" />
      <Files>
        <File FileName="move_tree.nsbmd" />
        <File FileName="move_tree.nsbca" />
      </Files>
      <Setting Id="0">
        <U32 Hex="true" />
      </Setting>
      <Setting Id="1">
        <U32 Hex="true" />
      </Setting>
      <Setting Id="2">
        <U32 Hex="true" />
      </Setting>
      <Setting Id="3">
        <U32 Hex="true" />
      </Setting>
    </Object>
    <Object Id="A001" Name="Bat">
      <Picture>http://images4.wikia.nocookie.net/__cb20120702021217/fantendo/images/c/c5/Swooper_Small.png</Picture>
      <Files>
        <File FileName="basabasa.nsbmd" />
        <File FileName="basabasa.nsbtp" />
      </Files>
      <Setting Id="0">
        <U32 Hex="true" />
      </Setting>
      <Setting Id="1">
        <U32 Hex="true" />
      </Setting>
      <Setting Id="2">
        <U32 Hex="true" />
      </Setting>
      <Setting Id="3">
        <U32 Hex="true" />
      </Setting>
    </Object>
    <Object Id="9901" Name="Peach Gardens Monty Mole">
      <Files>
        <File FileName="choropu.nsbmd" />
        <File FileName="choropu.nsbtp" />
      </Files>
      <Setting Id="0">
        <U32 Hex="true" />
      </Setting>
      <Setting Id="1">
        <U32 Hex="true" />
      </Setting>
      <Setting Id="2">
        <U32 Hex="true" />
      </Setting>
      <Setting Id="3">
        <U32 Hex="true" />
      </Setting>
    </Object>
    <Object Id="9301" Name="Thwomp">
      <Picture>http://www.mariowiki.com/images/archive/6/64/20111028230352!Thwomp2.PNG</Picture>
      <Files>
        <File FileName="dossun.nsbmd" />
        <File FileName="dossun_shadow.nsbmd" />
      </Files>
      <Setting Id="0">
        <U32 Name="Unknown1" Hex="true" />
      </Setting>
      <Setting Id="1">
        <U32 Name="Unknown2" Hex="true" />
      </Setting>
      <Setting Id="2">
        <U32 Name="Unknown3" Hex="true" />
      </Setting>
      <Setting Id="3">
        <U32 Name="Unknown4" Hex="true" />
      </Setting>
    </Object>
    <Object Id="3D01" Name="Boo">
      <Picture>http://www.mariowiki.com/images/thumb/b/b0/BooNSMBU.png/140px-BooNSMBU.png</Picture>
      <Files>
        <File FileName="teresa.nsbmd" />
        <File FileName="teresa.nsbtp" />
      </Files>
      <Setting Id="0">
        <U32 Name="Unknown1" Hex="true" />
      </Setting>
      <Setting Id="1">
        <U32 Name="Unknown2" Hex="true" />
      </Setting>
      <Setting Id="2">
        <U32 Name="Unknown3" Hex="true" />
      </Setting>
      <Setting Id="3">
        <U32 Name="Unknown4" Hex="true" />
      </Setting>
    </Object>
  </Category>
  <Category Name="Water">
    <Object Id="0500" Name="Water Splash">
      <Description>The water splash when falling into water. The y-position of this object needs to be exactly the same as the water.</Description>
      <Picture>http://www.dshack.org/wiki/images/9/98/WaterSplash.png</Picture>
      <Files>
        <File FileName="water_efct.nsbmd" />
        <File FileName="water_efct.nsbca" />
        <File FileName="water_efct.nsbma" />
      </Files>
      <Setting Id="0">
        <U32 Hex="true" />
      </Setting>
      <Setting Id="1">
        <U32 Hex="true" />
      </Setting>
      <Setting Id="2">
        <U32 Hex="true" />
      </Setting>
      <Setting Id="3">
        <U32 Hex="true" />
      </Setting>
    </Object>
    <Object Id="0D00" Name="Puddle">
      <Files>
        <File FileName="puddle.nsbmd" />
      </Files>
      <Setting Id="0">
        <U32 Hex="true" />
      </Setting>
      <Setting Id="1">
        <U32 Hex="true" />
      </Setting>
      <Setting Id="2">
        <U32 Hex="true" />
      </Setting>
      <Setting Id="3">
        <U32 Hex="true" />
      </Setting>
    </Object>
    <Object Id="0200" Name="Waterfall Move Effect">
      <Description>Used in Yoshi Falls for the moving effect of the waterfall. This object is linked to colission type 0x11.</Description>
      <Files />
      <Setting Id="0">
        <S16 Name="Water Basic Effect ID" />
        <U16 Hex="true" />
      </Setting>
      <Setting Id="1">
        <U32 Hex="true" />
      </Setting>
      <Setting Id="2">
        <U32 Hex="true" />
      </Setting>
      <Setting Id="3">
        <U32 Hex="true" />
      </Setting>
    </Object>
    <Object Id="0300" Name="Delfino Square Water">
      <Description>The water used in Delfino Square</Description>
      <Files>
        <File FileName="town_waterA.nsbmd" />
        <File FileName="town_waterC.nsbmd" />
      </Files>
      <Setting Id="0">
        <U32 Hex="true" />
      </Setting>
      <Setting Id="1">
        <U32 Hex="true" />
      </Setting>
      <Setting Id="2">
        <U32 Hex="true" />
      </Setting>
      <Setting Id="3">
        <U32 Hex="true" />
      </Setting>
    </Object>
    <Object Id="0100" Name="Cheep Cheep Beach Water">
      <Description>Water used in Cheep Cheep Beach. The y-position of this object doesn't affect the position since it's stored in the arm9.</Description>
      <Files>
        <File FileName="beach_waterA.nsbmd" />
        <File FileName="beach_waterC.nsbmd" />
      </Files>
      <Setting Id="0">
        <U32 Name="Unknown1" Hex="true" />
      </Setting>
      <Setting Id="1">
        <U32 Name="Unknown2" Hex="true" />
      </Setting>
      <Setting Id="2">
        <U32 Name="Unknown3" Hex="true" />
      </Setting>
      <Setting Id="3">
        <U32 Name="Unknown4" Hex="true" />
      </Setting>
    </Object>
    <Object Id="0600" Name="GCN Yoshi Circuit Water">
      <Description>The water used in GCN Yoshi Circuit.</Description>
      <Files>
        <File FileName="yoshi_waterC.nsbmd" />
      </Files>
      <Setting Id="0">
        <U32 Name="Unknown1" Hex="true" />
      </Setting>
      <Setting Id="1">
        <U32 Name="Unknown2" Hex="true" />
      </Setting>
      <Setting Id="2">
        <U32 Name="Unknown3" Hex="true" />
      </Setting>
      <Setting Id="3">
        <U32 Name="Unknown4" Hex="true" />
      </Setting>
    </Object>
    <Object Id="0900" Name="N64 Hyudoro Water">
      <Files>
        <File FileName="hyudoro_waterA.nsbmd" />
        <File FileName="hyudoro_waterC.nsbmd" />
      </Files>
      <Setting Id="0">
        <U32 Name="Unknown1" Hex="true" />
      </Setting>
      <Setting Id="1">
        <U32 Name="Unknown2" Hex="true" />
      </Setting>
      <Setting Id="2">
        <U32 Name="Unknown3" Hex="true" />
      </Setting>
      <Setting Id="3">
        <U32 Name="Unknown4" Hex="true" />
      </Setting>
    </Object>
    <Object Id="0C00" Name="Mini Stage 3 Water">
      <Files>
        <File FileName="mini_stage3_waterA.nsbmd" />
        <File FileName="mini_stage3_waterC.nsbmd" />
      </Files>
      <Setting Id="0">
        <U32 Name="Unknown1" Hex="true" />
      </Setting>
      <Setting Id="1">
        <U32 Name="Unknown2" Hex="true" />
      </Setting>
      <Setting Id="2">
        <U32 Name="Unknown3" Hex="true" />
      </Setting>
      <Setting Id="3">
        <U32 Name="Unknown4" Hex="true" />
      </Setting>
    </Object>
    <Object Id="0E00" Name="Lava Splash">
      <Files>
        <File FileName="water_efct.nsbmd" />
        <File FileName="water_efct.nsbca" />
        <File FileName="water_efct.nsbma" />
      </Files>
      <Setting Id="0">
        <U32 Name="Unknown1" Hex="true" />
      </Setting>
      <Setting Id="1">
        <U32 Name="Unknown2" Hex="true" />
      </Setting>
      <Setting Id="2">
        <U32 Name="Unknown3" Hex="true" />
      </Setting>
      <Setting Id="3">
        <U32 Name="Unknown4" Hex="true" />
      </Setting>
    </Object>
    <Object Id="0F00" Name="N64 Hyudoro Splash">
      <Files>
        <File FileName="water_efct.nsbmd" />
        <File FileName="water_efct.nsbca" />
        <File FileName="water_efct.nsbma" />
      </Files>
      <Setting Id="0">
        <U32 Name="Unknown1" Hex="true" />
      </Setting>
      <Setting Id="1">
        <U32 Name="Unknown2" Hex="true" />
      </Setting>
      <Setting Id="2">
        <U32 Name="Unknown3" Hex="true" />
      </Setting>
      <Setting Id="3">
        <U32 Name="Unknown4" Hex="true" />
      </Setting>
    </Object>
  </Category>
  <Category Name="Scenary">
    <Object Id="6700" Name="Wooden Box">
      <Picture>http://www.dshack.org/wiki/images/2/2b/Box.png</Picture>
      <Files>
        <File FileName="woodbox1.nsbmd" />
      </Files>
      <Setting Id="0">
        <U32 Hex="true" />
      </Setting>
      <Setting Id="1">
        <U32 Hex="true" />
      </Setting>
      <Setting Id="2">
        <U32 Hex="true" />
      </Setting>
      <Setting Id="3">
        <U32 Hex="true" />
      </Setting>
    </Object>
    <Object Id="4901" Name="Yoshi Falls Egg">
      <Picture>http://www.dshack.org/wiki/images/2/26/Egg.png</Picture>
      <Files>
        <File FileName="BankEgg1.nsbmd" />
      </Files>
      <Setting Id="0">
        <U32 Hex="true" />
      </Setting>
      <Setting Id="1">
        <U32 Hex="true" />
      </Setting>
      <Setting Id="2">
        <U32 Hex="true" />
      </Setting>
      <Setting Id="3">
        <U32 Hex="true" />
      </Setting>
    </Object>
    <Object Id="CC00" Name="Delfino Square Bridge">
      <Picture>http://www.mariowiki.com/images/0/03/DelfinosquareDS.png</Picture>
      <Files>
        <File FileName="bridge.nsbmd" />
        <File FileName="bridge.nsbca" />
      </Files>
      <Setting Id="0">
        <U32 Hex="true" />
      </Setting>
      <Setting Id="1">
        <U32 Hex="true" />
      </Setting>
      <Setting Id="2">
        <U32 Hex="true" />
      </Setting>
      <Setting Id="3">
        <U32 Hex="true" />
      </Setting>
    </Object>
    <Object Id="5701" Name="Pianta">
      <Picture>http://www.mariowiki.com/images/e/e9/PiantaPhotoThing.png</Picture>
      <Files>
        <File FileName="TownMonte.nsbmd" />
        <File FileName="TownMonte.nsbtp" />
      </Files>
      <Setting Id="0">
        <U32 Hex="true" />
      </Setting>
      <Setting Id="1">
        <U32 Hex="true" />
      </Setting>
      <Setting Id="2">
        <U32 Hex="true" />
      </Setting>
      <Setting Id="3">
        <U32 Hex="true" />
      </Setting>
    </Object>
    <Object Id="A401" Name="Flame">
      <Files>
        <File FileName="mkd_ef_burner.nsbmd" />
        <File FileName="mkd_ef_burner.nsbta" />
      </Files>
      <Setting Id="0">
        <U32 Hex="true" />
      </Setting>
      <Setting Id="1">
        <U32 Hex="true" />
      </Setting>
      <Setting Id="2">
        <U32 Hex="true" />
      </Setting>
      <Setting Id="3">
        <U32 Hex="true" />
      </Setting>
    </Object>
    <Object Id="AF01" Name="Rotating Fireballs">
      <Files>
        <File FileName="fireball2.nsbmd" />
      </Files>
      <Setting Id="0">
        <U16 Name="Nr of Arms/Fireballs" />
        <U16 Name="Radius" />
      </Setting>
      <Setting Id="1">
        <U16 Name="Rotation Speed" />
        <U16 Name="Spiral" />
      </Setting>
      <Setting Id="2">
        <U32 Name="Unknown3" Hex="true" />
      </Setting>
      <Setting Id="3">
        <U32 Name="Unknown4" Hex="true" />
      </Setting>
    </Object>
    <Category Name="Trees">
      <Object Id="2D01" Name="Beach Tree (Non-Solid)">
        <Picture>http://www.dshack.org/wiki/images/3/3a/BeachTree.png</Picture>
        <Files>
          <File FileName="BeachTree1.nsbmd" />
        </Files>
        <Setting Id="0">
          <U32 Hex="true" />
        </Setting>
        <Setting Id="1">
          <U32 Hex="true" />
        </Setting>
        <Setting Id="2">
          <U32 Hex="true" />
        </Setting>
        <Setting Id="3">
          <U32 Hex="true" />
        </Setting>
      </Object>
      <Object Id="2E01" Name="Beach Tree">
        <Picture>http://www.dshack.org/wiki/images/3/3a/BeachTree.png</Picture>
        <Files>
          <File FileName="BeachTree1.nsbmd" />
        </Files>
        <Setting Id="0">
          <U32 Hex="true" />
        </Setting>
        <Setting Id="1">
          <U32 Hex="true" />
        </Setting>
        <Setting Id="2">
          <U32 Hex="true" />
        </Setting>
        <Setting Id="3">
          <U32 Hex="true" />
        </Setting>
      </Object>
      <Object Id="4501" Name="Delfino Square Tree">
        <Files>
          <File FileName="TownTree1.nsbmd" />
        </Files>
        <Setting Id="0">
          <U32 Hex="true" />
        </Setting>
        <Setting Id="1">
          <U32 Hex="true" />
        </Setting>
        <Setting Id="2">
          <U32 Hex="true" />
        </Setting>
        <Setting Id="3">
          <U32 Hex="true" />
        </Setting>
      </Object>
      <Object Id="3E01" Name="Yoshi Falls Tree">
        <Files>
          <File FileName="Bank_Tree1.nsbmd" />
        </Files>
        <Setting Id="0">
          <U32 Hex="true" />
        </Setting>
        <Setting Id="1">
          <U32 Hex="true" />
        </Setting>
        <Setting Id="2">
          <U32 Hex="true" />
        </Setting>
        <Setting Id="3">
          <U32 Hex="true" />
        </Setting>
      </Object>
      <Object Id="3F01" Name="Peach Gardens Tree (Non-Solid)">
        <Files>
          <File FileName="GardenTree1.nsbmd" />
        </Files>
        <Setting Id="0">
          <U32 Hex="true" />
        </Setting>
        <Setting Id="1">
          <U32 Hex="true" />
        </Setting>
        <Setting Id="2">
          <U32 Hex="true" />
        </Setting>
        <Setting Id="3">
          <U32 Hex="true" />
        </Setting>
      </Object>
      <Object Id="4601" Name="DK Pass Tree">
        <Files>
          <File FileName="Snow_Tree1.nsbmd" />
        </Files>
        <Setting Id="0">
          <U32 Hex="true" />
        </Setting>
        <Setting Id="1">
          <U32 Hex="true" />
        </Setting>
        <Setting Id="2">
          <U32 Hex="true" />
        </Setting>
        <Setting Id="3">
          <U32 Hex="true" />
        </Setting>
      </Object>
      <Object Id="4801" Name="Dessert Hills Tree">
        <Files>
          <File FileName="DeTree1.nsbmd" />
        </Files>
        <Setting Id="0">
          <U32 Hex="true" />
        </Setting>
        <Setting Id="1">
          <U32 Hex="true" />
        </Setting>
        <Setting Id="2">
          <U32 Hex="true" />
        </Setting>
        <Setting Id="3">
          <U32 Hex="true" />
        </Setting>
      </Object>
      <Object Id="3801" Name="Peach Gardens Tree">
        <Files>
          <File FileName="GardenTree1.nsbmd" />
        </Files>
        <Setting Id="0">
          <U32 Hex="true" />
        </Setting>
        <Setting Id="1">
          <U32 Hex="true" />
        </Setting>
        <Setting Id="2">
          <U32 Hex="true" />
        </Setting>
        <Setting Id="3">
          <U32 Hex="true" />
        </Setting>
      </Object>
      <Object Id="4201" Name="Mario Circuit Tree">
        <Files>
          <File FileName="MarioTree3.nsbmd" />
        </Files>
        <Setting Id="0">
          <U32 Hex="true" />
        </Setting>
        <Setting Id="1">
          <U32 Hex="true" />
        </Setting>
        <Setting Id="2">
          <U32 Hex="true" />
        </Setting>
        <Setting Id="3">
          <U32 Hex="true" />
        </Setting>
      </Object>
    </Category>
    <Category Name="Traffic">
      <Object Id="9C01" Name="Truck">
        <Picture>http://www.dshack.org/wiki/images/0/01/Truck.png</Picture>
        <Files>
          <File FileName="truck_a.nsbmd" />
          <File FileName="truck_a_shadow.nsbmd" />
          <File FileName="car_tire.nsbmd" />
          <File FileName="truck_a.nsbtp" />
        </Files>
        <Setting Id="0">
          <S16 Name="Route Speed" />
          <S16 Name="Route Start Index" />
        </Setting>
        <Setting Id="1">
          <S16 Name="NSBTP Frame" />
          <U16 Hex="true" />
        </Setting>
        <Setting Id="2">
          <U32 Hex="true" />
        </Setting>
        <Setting Id="3">
          <U32 Hex="true" />
        </Setting>
      </Object>
    </Category>
    <Category Name="Waluigi Pinball">
      <Object Id="A801" Name="Bound">
        <Files>
          <File FileName="bound.nsbmd" />
          <File FileName="bound.nsbtp" />
        </Files>
        <Setting Id="0">
          <U32 Name="Unknown1" Hex="true" />
        </Setting>
        <Setting Id="1">
          <U32 Name="Unknown2" Hex="true" />
        </Setting>
        <Setting Id="2">
          <U32 Name="Unknown3" Hex="true" />
        </Setting>
        <Setting Id="3">
          <U32 Name="Unknown4" Hex="true" />
        </Setting>
      </Object>
      <Object Id="A901" Name="Flipper">
        <Files />
        <Setting Id="0">
          <U32 Name="Unknown1" Hex="true" />
        </Setting>
        <Setting Id="1">
          <U32 Name="Unknown2" Hex="true" />
        </Setting>
        <Setting Id="2">
          <U32 Name="Unknown3" Hex="true" />
        </Setting>
        <Setting Id="3">
          <U32 Name="Unknown4" Hex="true" />
        </Setting>
      </Object>
      <Object Id="B001" Name="Moving Iron Ball">
        <Files />
        <Setting Id="0">
          <U32 Name="Unknown1" Hex="true" />
        </Setting>
        <Setting Id="1">
          <U32 Name="Unknown2" Hex="true" />
        </Setting>
        <Setting Id="2">
          <U32 Name="Unknown3" Hex="true" />
        </Setting>
        <Setting Id="3">
          <U32 Name="Unknown4" Hex="true" />
        </Setting>
      </Object>
      <Object Id="B301" Name="Iron Ball">
        <Files />
        <Setting Id="0">
          <U32 Name="Unknown1" Hex="true" />
        </Setting>
        <Setting Id="1">
          <U32 Name="Unknown2" Hex="true" />
        </Setting>
        <Setting Id="2">
          <U32 Name="Unknown3" Hex="true" />
        </Setting>
        <Setting Id="3">
          <U32 Name="Unknown4" Hex="true" />
        </Setting>
      </Object>
    </Category>
    <Category Name="Bowser Castle">
      <Object Id="CA00" Name="Moving Platforms">
        <Description>The moving platforms used in bowser castle.</Description>
        <Route Required="true" />
        <Files>
          <File FileName="koopa_block.nsbmd" />
        </Files>
        <Setting Id="0">
          <U32 Name="Unknown1" Hex="true" />
        </Setting>
        <Setting Id="1">
          <U32 Name="Unknown2" Hex="true" />
        </Setting>
        <Setting Id="2">
          <U32 Name="Unknown3" Hex="true" />
        </Setting>
        <Setting Id="3">
          <U32 Name="Unknown4" Hex="true" />
        </Setting>
      </Object>
      <Object Id="D000" Name="Rotary Room">
        <Files>
          <File FileName="rotary_room.nsbmd" />
        </Files>
        <Setting Id="0">
          <U32 Name="Unknown1" Hex="true" />
        </Setting>
        <Setting Id="1">
          <U32 Name="Unknown2" Hex="true" />
        </Setting>
        <Setting Id="2">
          <U32 Name="Unknown3" Hex="true" />
        </Setting>
        <Setting Id="3">
          <U32 Name="Unknown4" Hex="true" />
        </Setting>
      </Object>
      <Object Id="D100" Name="Rotary Bridge">
        <Files>
          <File FileName="rotary_bridge.nsbmd" />
        </Files>
        <Setting Id="0">
          <U32 Name="Unknown1" Hex="true" />
        </Setting>
        <Setting Id="1">
          <U32 Name="Unknown2" Hex="true" />
        </Setting>
        <Setting Id="2">
          <U32 Name="Unknown3" Hex="true" />
        </Setting>
        <Setting Id="3">
          <U32 Name="Unknown4" Hex="true" />
        </Setting>
      </Object>
    </Category>
    <Category Name="Tick-Tock Clock">
      <Object Id="CB00" Name="Gear">
        <Files>
          <File FileName="gear_black.nsbmd" />
          <File FileName="gear_white.nsbmd" />
        </Files>
        <Setting Id="0">
          <U32 Name="Unknown1" Hex="true" />
        </Setting>
        <Setting Id="1">
          <U32 Name="Unknown2" Hex="true" />
        </Setting>
        <Setting Id="2">
          <U32 Name="Unknown3" Hex="true" />
        </Setting>
        <Setting Id="3">
          <U32 Name="Unknown4" Hex="true" />
        </Setting>
      </Object>
      <Object Id="CF00" Name="Pendulum">
        <Files>
          <File FileName="pendulum.nsbmd" />
          <File FileName="pendulum_shadow.nsbmd" />
        </Files>
        <Setting Id="0">
          <U32 Name="Unknown1" Hex="true" />
        </Setting>
        <Setting Id="1">
          <U32 Name="Unknown2" Hex="true" />
        </Setting>
        <Setting Id="2">
          <U32 Name="Unknown3" Hex="true" />
        </Setting>
        <Setting Id="3">
          <U32 Name="Unknown4" Hex="true" />
        </Setting>
      </Object>
      <Object Id="CD00" Name="Second Hand">
        <Files>
          <File FileName="second_hand.nsbmd" />
        </Files>
        <Setting Id="0">
          <U32 Name="Unknown1" Hex="true" />
        </Setting>
        <Setting Id="1">
          <U32 Name="Unknown2" Hex="true" />
        </Setting>
        <Setting Id="2">
          <U32 Name="Unknown3" Hex="true" />
        </Setting>
        <Setting Id="3">
          <U32 Name="Unknown4" Hex="true" />
        </Setting>
      </Object>
      <Object Id="CE00" Name="Test Gear">
        <Files>
          <File FileName="test_cylinder.nsbmd" />
        </Files>
        <Setting Id="0">
          <U32 Name="Unknown1" Hex="true" />
        </Setting>
        <Setting Id="1">
          <U32 Name="Unknown2" Hex="true" />
        </Setting>
        <Setting Id="2">
          <U32 Name="Unknown3" Hex="true" />
        </Setting>
        <Setting Id="3">
          <U32 Name="Unknown4" Hex="true" />
        </Setting>
      </Object>
    </Category>
    <Category Name="Effects">
      <Object Id="B601" Name="Jumping Fireball">
        <Picture>http://www.dshack.org/wiki/images/a/ae/Fireball.png</Picture>
        <Files />
        <Setting Id="0">
          <U32 Name="Unknown1" Hex="true" />
        </Setting>
        <Setting Id="1">
          <U32 Name="Unknown2" Hex="true" />
        </Setting>
        <Setting Id="2">
          <U32 Name="Unknown3" Hex="true" />
        </Setting>
        <Setting Id="3">
          <U32 Name="Unknown4" Hex="true" />
        </Setting>
      </Object>
    </Category>
  </Category>
  <Category Name="Battle Mode">
    <Object Id="6A00" Name="Shine">
      <Picture>http://www.mariowiki.com/images/thumb/c/c7/FI_Shine.png/170px-FI_Shine.png</Picture>
      <Files>
        <File FileName="shine16.nsbmd" />
        <File FileName="shine16.nsbtp" />
      </Files>
      <Setting Id="0">
        <U32 Name="Unknown1" Hex="true" />
      </Setting>
      <Setting Id="1">
        <U32 Name="Unknown2" Hex="true" />
      </Setting>
      <Setting Id="2">
        <U32 Name="Unknown3" Hex="true" />
      </Setting>
      <Setting Id="3">
        <U32 Name="Unknown4" Hex="true" />
      </Setting>
    </Object>
    <Object Id="6C00" Name="Balloon">
      <Description>The balloons for balloon battle.</Description>
      <Files>
        <File FileName="balloon.nsbmd" />
        <File FileName="balloon.nsbtp" />
      </Files>
      <Setting Id="0">
        <U32 Name="Unknown1" Hex="true" />
      </Setting>
      <Setting Id="1">
        <U32 Name="Unknown2" Hex="true" />
      </Setting>
      <Setting Id="2">
        <U32 Name="Unknown3" Hex="true" />
      </Setting>
      <Setting Id="3">
        <U32 Name="Unknown4" Hex="true" />
      </Setting>
    </Object>
    <Object Id="7000" Name="Shine Balloon">
      <Files>
        <File FileName="shine_balloon.nsbmd" />
      </Files>
      <Setting Id="0">
        <U32 Name="Unknown1" Hex="true" />
      </Setting>
      <Setting Id="1">
        <U32 Name="Unknown2" Hex="true" />
      </Setting>
      <Setting Id="2">
        <U32 Name="Unknown3" Hex="true" />
      </Setting>
      <Setting Id="3">
        <U32 Name="Unknown4" Hex="true" />
      </Setting>
    </Object>
  </Category>
</Root>